{"files":{"apps/site/.next/server/pages":{"size":0,"mtime_nanos":0,"mode":0,"is_dir":true},"apps/site/.next/export-marker.json":{"size":94,"mtime_nanos":1774324993119841800,"mode":420,"is_dir":false},"apps/site/.next/server/app/_not-found.rsc":{"size":3621,"mtime_nanos":1774324992437873600,"mode":420,"is_dir":false},"apps/site/.next/server/app/index.rsc":{"size":2255,"mtime_nanos":1774324992399637300,"mode":420,"is_dir":false},"apps/site/.next/cache":{"size":0,"mtime_nanos":0,"mode":0,"is_dir":true},"apps/site/.next/server/pages/_app.js":{"size":3291,"mtime_nanos":1774324977662380600,"mode":420,"is_dir":false},"apps/site/.next/server/pages/_document.js.nft.json":{"size":4434,"mtime_nanos":1774324997948132700,"mode":420,"is_dir":false},"apps/site/.next/cache/webpack/server-production/index.pack":{"size":1988641,"mtime_nanos":1774324979145169000,"mode":420,"is_dir":false},"apps/site/.next/static/GNlIkyeyHJDymekN9QCwj":{"size":0,"mtime_nanos":0,"mode":0,"is_dir":true},"apps/site/.next/static/chunks/app":{"size":0,"mtime_nanos":0,"mode":0,"is_dir":true},"apps/site/.next/server/app/index.html":{"size":4162,"mtime_nanos":1774324992403002200,"mode":420,"is_dir":false},"apps/site/.next/server/middleware-build-manifest.js":{"size":888,"mtime_nanos":1774324985847603300,"mode":420,"is_dir":false},"apps/site/.next/static/chunks/main-app-357b16f05c248fb1.js":{"size":463,"mtime_nanos":1774324985838609700,"mode":420,"is_dir":false},"apps/site/.next/static/chunks/pages/_app-1b77bd37fc4f49dd.js":{"size":279,"mtime_nanos":1774324985838609700,"mode":420,"is_dir":false},"apps/site/.next/trace":{"size":290554,"mtime_nanos":1774324997980430900,"mode":420,"is_dir":false},"apps/site/.next/types/package.json":{"size":18,"mtime_nanos":1774324977673404200,"mode":420,"is_dir":false},"apps/site/dist/assets":{"size":0,"mtime_nanos":0,"mode":0,"is_dir":true},"apps/site/.next/cache/webpack/server-production/0.pack":{"size":7688623,"mtime_nanos":1774324979156793400,"mode":420,"is_dir":false},"apps/site/.next/next-minimal-server.js.nft.json":{"size":9847,"mtime_nanos":1774324997975439800,"mode":420,"is_dir":false},"apps/site/.next/server/app/_not-found":{"size":0,"mtime_nanos":0,"mode":0,"is_dir":true},"apps/site/.next/static/chunks/framework-bef83a85c94ff7de.js":{"size":139981,"mtime_nanos":1774324985838609700,"mode":420,"is_dir":false},"apps/site/.next/server/middleware-react-loadable-manifest.js":{"size":36,"mtime_nanos":1774324985788392300,"mode":420,"is_dir":false},"apps/site/.next/server/pages/_app.js.nft.json":{"size":901,"mtime_nanos":1774324997948132700,"mode":420,"is_dir":false},"apps/site/.turbo/turbo-build.log":{"size":944,"mtime_nanos":1774324998050211600,"mode":420,"is_dir":false},"apps/site/.next/cache/webpack/edge-server-production/index.pack":{"size":22277,"mtime_nanos":1774324981268654900,"mode":420,"is_dir":false},"apps/site/dist/assets/index-yM0MXSfV.css":{"size":1110,"mtime_nanos":1774319653940694400,"mode":420,"is_dir":false},"apps/site/.next/cache/swc/plugins/v7_windows_x86_64_0.106.15":{"size":0,"mtime_nanos":0,"mode":0,"is_dir":true},"apps/site/dist":{"size":0,"mtime_nanos":0,"mode":0,"is_dir":true},"apps/site/.next/cache/.tsbuildinfo":{"size":109264,"mtime_nanos":1774324990064276000,"mode":420,"is_dir":false},"apps/site/.next/cache/swc":{"size":0,"mtime_nanos":0,"mode":0,"is_dir":true},"apps/site/.next/cache/webpack/client-production/0.pack":{"size":12745292,"mtime_nanos":1774324988154571400,"mode":420,"is_dir":false},"apps/site/.next/server/server-reference-manifest.js":{"size":123,"mtime_nanos":1774324977671376700,"mode":420,"is_dir":false},"apps/site/.next/static/chunks":{"size":0,"mtime_nanos":0,"mode":0,"is_dir":true},"apps/site/.next/static/chunks/app/page-76e8210cac371eb8.js":{"size":160,"mtime_nanos":1774324985839605500,"mode":420,"is_dir":false},"apps/site/.next/server/app/_not-found.html":{"size":6526,"mtime_nanos":1774324992440866100,"mode":420,"is_dir":false},"apps/site/.next/server/chunks":{"size":0,"mtime_nanos":0,"mode":0,"is_dir":true},"apps/site/.next/server/app-paths-manifest.json":{"size":76,"mtime_nanos":1774324980863965400,"mode":420,"is_dir":false},"apps/site/.next/server/middleware-manifest.json":{"size":83,"mtime_nanos":1774324980883201700,"mode":420,"is_dir":false},"apps/site/.next/routes-manifest.json":{"size":721,"mtime_nanos":1774324973868120000,"mode":420,"is_dir":false},"apps/site/.next/server/app/_not-found/page.js":{"size":3343,"mtime_nanos":1774324977668371100,"mode":420,"is_dir":false},"apps/site/.next/server/pages/_error.js":{"size":8622,"mtime_nanos":1774324977662380600,"mode":420,"is_dir":false},"apps/site/.next/types/app/page.ts":{"size":3481,"mtime_nanos":1774324977676411200,"mode":420,"is_dir":false},"apps/site/.next/app-path-routes-manifest.json":{"size":46,"mtime_nanos":1774324990292691900,"mode":420,"is_dir":false},"apps/site/.next/static/chunks/app/_not-found/page-58883785aa9eaa7d.js":{"size":1745,"mtime_nanos":1774324985846606200,"mode":420,"is_dir":false},"apps/site/.next/server/app/_not-found.meta":{"size":142,"mtime_nanos":1774324992442866300,"mode":420,"is_dir":false},"apps/site/.next/server/app/page_client-reference-manifest.js":{"size":3750,"mtime_nanos":1774324985852600500,"mode":420,"is_dir":false},"apps/site/.next/types":{"size":0,"mtime_nanos":0,"mode":0,"is_dir":true},"apps/site/.next/cache/webpack/server-production":{"size":0,"mtime_nanos":0,"mode":0,"is_dir":true},"apps/site/.next/server/pages/_document.js":{"size":378,"mtime_nanos":1774324977662380600,"mode":420,"is_dir":false},"apps/site/.next/static":{"size":0,"mtime_nanos":0,"mode":0,"is_dir":true},"apps/site/.next/static/chunks/app/layout-cf9f35b4a8dda1c0.js":{"size":230,"mtime_nanos":1774324985839605500,"mode":420,"is_dir":false},"apps/site/.next/server/chunks/font-manifest.json":{"size":2,"mtime_nanos":1774324977660377600,"mode":420,"is_dir":false},"apps/site/.next/server/pages-manifest.json":{"size":111,"mtime_nanos":1774324993004170100,"mode":420,"is_dir":false},"apps/site/.next/server/next-font-manifest.js":{"size":106,"mtime_nanos":1774324985849615100,"mode":420,"is_dir":false},"apps/site/.next/cache/webpack/edge-server-production":{"size":0,"mtime_nanos":0,"mode":0,"is_dir":true},"apps/site/dist/assets/index-DaXL01bZ.js":{"size":143498,"mtime_nanos":1774319653940694400,"mode":420,"is_dir":false},"apps/site/.next/static/chunks/webpack-52e4406708ff765d.js":{"size":3446,"mtime_nanos":1774324985837601700,"mode":420,"is_dir":false},"apps/site/.next/cache/swc/plugins":{"size":0,"mtime_nanos":0,"mode":0,"is_dir":true},"apps/site/.next/server/app/page.js":{"size":2483,"mtime_nanos":1774324977662380600,"mode":420,"is_dir":false},"apps/site/.next/package.json":{"size":20,"mtime_nanos":1774324973865743800,"mode":420,"is_dir":false},"apps/site/.next/server/app/page.js.nft.json":{"size":2274,"mtime_nanos":1774324997948132700,"mode":420,"is_dir":false},"apps/site/.next/static/chunks/12794e6a-0ced994edc779baf.js":{"size":172831,"mtime_nanos":1774324985839605500,"mode":420,"is_dir":false},"apps/site/.next/cache/webpack/client-production/index.pack":{"size":2805564,"mtime_nanos":1774324988140498600,"mode":420,"is_dir":false},"apps/site/.next/next-server.js.nft.json":{"size":73002,"mtime_nanos":1774324997974439600,"mode":420,"is_dir":false},"apps/site/.next/static/chunks/app/_not-found":{"size":0,"mtime_nanos":0,"mode":0,"is_dir":true},"apps/site/.next/server/app/_not-found/page.js.nft.json":{"size":2271,"mtime_nanos":1774324997948132700,"mode":420,"is_dir":false},"apps/site/.next/server/pages/404.html":{"size":6526,"mtime_nanos":1774324992440866100,"mode":420,"is_dir":false},"apps/site/.next/static/chunks/polyfills-42372ed130431b0a.js":{"size":112594,"mtime_nanos":1774324985838609700,"mode":420,"is_dir":false},"apps/site/.next/react-loadable-manifest.json":{"size":2,"mtime_nanos":1774324985785137100,"mode":420,"is_dir":false},"apps/site/.next/static/chunks/498-4a580e5eda8e9312.js":{"size":123535,"mtime_nanos":1774324985838609700,"mode":420,"is_dir":false},"apps/site/.next/static/css":{"size":0,"mtime_nanos":0,"mode":0,"is_dir":true},"apps/site/.next/cache/webpack":{"size":0,"mtime_nanos":0,"mode":0,"is_dir":true},"apps/site/.next/static/css/8dcb11003425c484.css":{"size":215,"mtime_nanos":1774324985849615100,"mode":420,"is_dir":false},"apps/site/.next/server/pages/_error.js.nft.json":{"size":4269,"mtime_nanos":1774324997948132700,"mode":420,"is_dir":false},"apps/site/.next/static/GNlIkyeyHJDymekN9QCwj/_buildManifest.js":{"size":224,"mtime_nanos":1774324985849615100,"mode":420,"is_dir":false},"apps/site/.next/static/chunks/pages/_error-3e94cae9729b376b.js":{"size":247,"mtime_nanos":1774324985838609700,"mode":420,"is_dir":false},"apps/site/.next/static/chunks/main-ca6969288864e8e9.js":{"size":110844,"mtime_nanos":1774324985838609700,"mode":420,"is_dir":false},"apps/site/.next/types/app":{"size":0,"mtime_nanos":0,"mode":0,"is_dir":true},"apps/site/dist/index.html":{"size":430,"mtime_nanos":1774319653939702500,"mode":420,"is_dir":false},"apps/site/.next/cache/webpack/edge-server-production/0.pack":{"size":274,"mtime_nanos":1774324981264461900,"mode":420,"is_dir":false},"apps/site/.next/server":{"size":0,"mtime_nanos":0,"mode":0,"is_dir":true},"apps/site/.next/build-manifest.json":{"size":968,"mtime_nanos":1774324985839605500,"mode":420,"is_dir":false},"apps/site/.next/app-build-manifest.json":{"size":911,"mtime_nanos":1774324985848607000,"mode":420,"is_dir":false},"apps/site/.next/server/interception-route-rewrite-manifest.js":{"size":48,"mtime_nanos":1774324980883201700,"mode":420,"is_dir":false},"apps/site/.next/prerender-manifest.json":{"size":526,"mtime_nanos":1774324993035255600,"mode":420,"is_dir":false},"apps/site/.next/server/app/_not-found/page_client-reference-manifest.js":{"size":3836,"mtime_nanos":1774324985852600500,"mode":420,"is_dir":false},"apps/site/.next/server/app/index.meta":{"size":80,"mtime_nanos":1774324992408898300,"mode":420,"is_dir":false},"apps/site/.next/server/chunks/108.js":{"size":33646,"mtime_nanos":1774324977662380600,"mode":420,"is_dir":false},"apps/site/.next/server/functions-config-manifest.json":{"size":28,"mtime_nanos":1774324991330431500,"mode":420,"is_dir":false},"apps/site/.next/server/next-font-manifest.json":{"size":77,"mtime_nanos":1774324985849615100,"mode":420,"is_dir":false},"apps/site/.next/required-server-files.json":{"size":4685,"mtime_nanos":1774324991360622400,"mode":420,"is_dir":false},"apps/site/.next":{"size":0,"mtime_nanos":0,"mode":0,"is_dir":true},"apps/site/.next/server/chunks/874.js":{"size":150611,"mtime_nanos":1774324977661375800,"mode":420,"is_dir":false},"apps/site/.next/server/webpack-runtime.js":{"size":1459,"mtime_nanos":1774324977662380600,"mode":420,"is_dir":false},"apps/site/.next/server/pages/500.html":{"size":1995,"mtime_nanos":1774324992394827400,"mode":420,"is_dir":false},"apps/site/.next/static/GNlIkyeyHJDymekN9QCwj/_ssgManifest.js":{"size":80,"mtime_nanos":1774324993065161800,"mode":420,"is_dir":false},"apps/site/.next/static/chunks/pages":{"size":0,"mtime_nanos":0,"mode":0,"is_dir":true},"apps/site/.next/types/app/layout.ts":{"size":3493,"mtime_nanos":1774324977676411200,"mode":420,"is_dir":false},"apps/site/.next/images-manifest.json":{"size":511,"mtime_nanos":1774324993087612500,"mode":420,"is_dir":false},"apps/site/.next/cache/webpack/client-production":{"size":0,"mtime_nanos":0,"mode":0,"is_dir":true},"apps/site/.next/server/server-reference-manifest.json":{"size":84,"mtime_nanos":1774324977671376700,"mode":420,"is_dir":false},"apps/site/.next/server/app":{"size":0,"mtime_nanos":0,"mode":0,"is_dir":true},"apps/site/.next/server/font-manifest.json":{"size":2,"mtime_nanos":1774324977662380600,"mode":420,"is_dir":false},"apps/site/.next/BUILD_ID":{"size":21,"mtime_nanos":1774324991356488200,"mode":420,"is_dir":false}},"order":["apps/site/.next","apps/site/.next/BUILD_ID","apps/site/.next/app-build-manifest.json","apps/site/.next/app-path-routes-manifest.json","apps/site/.next/build-manifest.json","apps/site/.next/cache","apps/site/.next/cache/.tsbuildinfo","apps/site/.next/cache/swc","apps/site/.next/cache/swc/plugins","apps/site/.next/cache/swc/plugins/v7_windows_x86_64_0.106.15","apps/site/.next/cache/webpack","apps/site/.next/cache/webpack/client-production","apps/site/.next/cache/webpack/client-production/0.pack","apps/site/.next/cache/webpack/client-production/index.pack","apps/site/.next/cache/webpack/edge-server-production","apps/site/.next/cache/webpack/edge-server-production/0.pack","apps/site/.next/cache/webpack/edge-server-production/index.pack","apps/site/.next/cache/webpack/server-production","apps/site/.next/cache/webpack/server-production/0.pack","apps/site/.next/cache/webpack/server-production/index.pack","apps/site/.next/export-marker.json","apps/site/.next/images-manifest.json","apps/site/.next/next-minimal-server.js.nft.json","apps/site/.next/next-server.js.nft.json","apps/site/.next/package.json","apps/site/.next/prerender-manifest.json","apps/site/.next/react-loadable-manifest.json","apps/site/.next/required-server-files.json","apps/site/.next/routes-manifest.json","apps/site/.next/server","apps/site/.next/server/app","apps/site/.next/server/app/_not-found","apps/site/.next/server/app/_not-found/page.js","apps/site/.next/server/app/_not-found/page.js.nft.json","apps/site/.next/server/app/_not-found/page_client-reference-manifest.js","apps/site/.next/server/app/_not-found.html","apps/site/.next/server/app/_not-found.meta","apps/site/.next/server/app/_not-found.rsc","apps/site/.next/server/app/index.html","apps/site/.next/server/app/index.meta","apps/site/.next/server/app/index.rsc","apps/site/.next/server/app/page.js","apps/site/.next/server/app/page.js.nft.json","apps/site/.next/server/app/page_client-reference-manifest.js","apps/site/.next/server/app-paths-manifest.json","apps/site/.next/server/chunks","apps/site/.next/server/chunks/108.js","apps/site/.next/server/chunks/874.js","apps/site/.next/server/chunks/font-manifest.json","apps/site/.next/server/font-manifest.json","apps/site/.next/server/functions-config-manifest.json","apps/site/.next/server/interception-route-rewrite-manifest.js","apps/site/.next/server/middleware-build-manifest.js","apps/site/.next/server/middleware-manifest.json","apps/site/.next/server/middleware-react-loadable-manifest.js","apps/site/.next/server/next-font-manifest.js","apps/site/.next/server/next-font-manifest.json","apps/site/.next/server/pages","apps/site/.next/server/pages/404.html","apps/site/.next/server/pages/500.html","apps/site/.next/server/pages/_app.js","apps/site/.next/server/pages/_app.js.nft.json","apps/site/.next/server/pages/_document.js","apps/site/.next/server/pages/_document.js.nft.json","apps/site/.next/server/pages/_error.js","apps/site/.next/server/pages/_error.js.nft.json","apps/site/.next/server/pages-manifest.json","apps/site/.next/server/server-reference-manifest.js","apps/site/.next/server/server-reference-manifest.json","apps/site/.next/server/webpack-runtime.js","apps/site/.next/static","apps/site/.next/static/GNlIkyeyHJDymekN9QCwj","apps/site/.next/static/GNlIkyeyHJDymekN9QCwj/_buildManifest.js","apps/site/.next/static/GNlIkyeyHJDymekN9QCwj/_ssgManifest.js","apps/site/.next/static/chunks","apps/site/.next/static/chunks/12794e6a-0ced994edc779baf.js","apps/site/.next/static/chunks/498-4a580e5eda8e9312.js","apps/site/.next/static/chunks/app","apps/site/.next/static/chunks/app/_not-found","apps/site/.next/static/chunks/app/_not-found/page-58883785aa9eaa7d.js","apps/site/.next/static/chunks/app/layout-cf9f35b4a8dda1c0.js","apps/site/.next/static/chunks/app/page-76e8210cac371eb8.js","apps/site/.next/static/chunks/framework-bef83a85c94ff7de.js","apps/site/.next/static/chunks/main-app-357b16f05c248fb1.js","apps/site/.next/static/chunks/main-ca6969288864e8e9.js","apps/site/.next/static/chunks/pages","apps/site/.next/static/chunks/pages/_app-1b77bd37fc4f49dd.js","apps/site/.next/static/chunks/pages/_error-3e94cae9729b376b.js","apps/site/.next/static/chunks/polyfills-42372ed130431b0a.js","apps/site/.next/static/chunks/webpack-52e4406708ff765d.js","apps/site/.next/static/css","apps/site/.next/static/css/8dcb11003425c484.css","apps/site/.next/trace","apps/site/.next/types","apps/site/.next/types/app","apps/site/.next/types/app/layout.ts","apps/site/.next/types/app/page.ts","apps/site/.next/types/package.json","apps/site/.turbo/turbo-build.log","apps/site/dist","apps/site/dist/assets","apps/site/dist/assets/index-DaXL01bZ.js","apps/site/dist/assets/index-yM0MXSfV.css","apps/site/dist/index.html"]}